utm_zone/__init__.py
utm_zone-1.0.1.dist-info/LICENSE
utm_zone-1.0.1.dist-info/METADATA
utm_zone-1.0.1.dist-info/WHEEL
utm_zone-1.0.1.dist-info/top_level.txt
utm_zone-1.0.1.dist-info/RECORD
