Metadata-Version: 2.1
Name: utm-zone
Version: 1.0.1
Summary: Find the UTM zone for your GeoJSON
Home-page: https://github.com/perliedman/py-utm-zone
Author: Per Liedman
Author-email: per@liedman.net
License: UNKNOWN
Platform: UNKNOWN
Classifier: Programming Language :: Python :: 3
Classifier: License :: OSI Approved :: ISC License (ISCL)
Classifier: Operating System :: OS Independent
Requires-Python: >=3
